{
  "Title": "LinguaCards (EN-RU)",
  "DeckID": "d9b8c7e2-1234-4f56-89ab-cdef01234567",
  "Description": "Memorize your words with Russian translations",
  "FromType": "TEXT",
  "ToType": "TEXT",
  "Items": [
    { "id": 0, "from": "grunt", "to": ["ворчать","хрюкать","ворчание"] },
    { "id": 1, "from": "bestowed", "to": ["дарованный","наделённый"] },
    { "id": 2, "from": "apart", "to": ["отдельно","врозь"] },
    { "id": 3, "from": "conjured", "to": ["заколдованный","вызывал"] },
    { "id": 4, "from": "mantle", "to": ["мантия","покров"] },
    { "id": 5, "from": "astry", "to": ["астры"] },
    { "id": 6, "from": "swam", "to": ["плавал","плавать"] },
    { "id": 7, "from": "cunt", "to": ["пизда"] },
    { "id": 8, "from": "assult", "to": ["нападение","нападать"] },
    { "id": 9, "from": "mend", "to": ["чинить","штопать"] },
    { "id": 10, "from": "incite", "to": ["подстрекать","разжигать"] },
    { "id": 11, "from": "deem", "to": ["считать","полагать"] },
    { "id": 12, "from": "Prudent", "to": ["благоразумный"] },
    { "id": 13, "from": "pup", "to": ["щенок"] },
    { "id": 14, "from": "Oaf", "to": ["грубиян","болван"] },
    { "id": 15, "from": "glorious", "to": ["славный","великолепный"] },
    { "id": 16, "from": "swiftly", "to": ["быстро","стремительно"] },
    { "id": 17, "from": "burden", "to": ["бремя","нагрузка"] },
    { "id": 18, "from": "harp", "to": ["арфа"] },
    { "id": 19, "from": "amend", "to": ["вносить поправки","исправлять"] },
    { "id": 20, "from": "apparently", "to": ["очевидно","по-видимому"] },
    { "id": 21, "from": "Yet", "to": ["еще","однако"] },
    { "id": 22, "from": "Deed", "to": ["поступок","документ"] },
    { "id": 23, "from": "delightful", "to": ["восхитительный","чудесный"] },
    { "id": 24, "from": "clings", "to": ["цепляться","прилипать"] },
    { "id": 25, "from": "humble", "to": ["скромный","смиренный"] },
    { "id": 26, "from": "summoned", "to": ["призванный","вызванный"] },
    { "id": 27, "from": "Revealed", "to": ["раскрытый","обнаруженный"] },
    { "id": 28, "from": "engage", "to": ["вовлекать","заниматься","помолвиться"] },
    { "id": 29, "from": "pity", "to": ["жалость","сожаление"] },
    { "id": 30, "from": "seldom", "to": ["редко"] },
    { "id": 31, "from": "unravel", "to": ["распутывать","разгадать"] },
    { "id": 32, "from": "gaze", "to": ["смотреть пристально","взгляд"] },
    { "id": 33, "from": "passion", "to": ["страсть","увлечение"] },
    { "id": 34, "from": "aedile", "to": ["эдиль"] },
    { "id": 35, "from": "linger", "to": ["задерживаться","медлить"] },
    { "id": 36, "from": "sway", "to": ["качаться","влиять"] },
    { "id": 37, "from": "clatter", "to": ["грохот","бряцание"] },
    { "id": 38, "from": "bond", "to": ["связь","обязательство","облигация"] }
  ]
}
