{
  "Title": "LinguaCards (RU-EN)",
  "DeckID": "e1f2d3c4-5678-90ab-cdef-1234567890ab",
  "Description": "Memorize your words with English translations",
  "FromType": "TEXT",
  "ToType": "TEXT",
  "Items": [
    { "id": 0, "from": ["ворчать","хрюкать","ворчание"], "to": ["grunt"] },
    { "id": 1, "from": ["дарованный","наделённый"], "to": ["bestowed"] },
    { "id": 2, "from": ["отдельно","врозь"], "to": ["apart"] },
    { "id": 3, "from": ["заколдованный","вызывал"], "to": ["conjured"] },
    { "id": 4, "from": ["мантия","покров"], "to": ["mantle"] },
    { "id": 5, "from": ["астры"], "to": ["aster"] },
    { "id": 6, "from": ["плавал","плавать"], "to": ["swam"] },
    { "id": 7, "from": ["нападение","нападать"], "to": ["assault"] },
    { "id": 8, "from": ["чинить","штопать"], "to": ["mend"] },
    { "id": 9, "from": ["подстрекать","разжигать"], "to": ["incite"] },
    { "id": 10, "from": ["считать","полагать"], "to": ["deem"] },
    { "id": 11, "from": ["благоразумный"], "to": ["prudent"] },
    { "id": 12, "from": ["щенок"], "to": ["pup"] },
    { "id": 13, "from": ["грубиян","болван"], "to": ["oaf"] },
    { "id": 14, "from": ["славный","великолепный"], "to": ["glorious"] },
    { "id": 15, "from": ["быстро","стремительно"], "to": ["swiftly"] },
    { "id": 16, "from": ["бремя","нагрузка"], "to": ["burden"] },
    { "id": 17, "from": ["арфа"], "to": ["harp"] },
    { "id": 18, "from": ["вносить поправки","исправлять"], "to": ["amend"] },
    { "id": 19, "from": ["очевидно","по-видимому"], "to": ["apparently"] },
    { "id": 20, "from": ["еще","однако"], "to": ["yet"] },
    { "id": 21, "from": ["поступок","документ"], "to": ["deed"] },
    { "id": 22, "from": ["восхитительный","чудесный"], "to": ["delightful"] },
    { "id": 23, "from": ["цепляться","прилипать"], "to": ["clings"] },
    { "id": 24, "from": ["скромный","смиренный"], "to": ["humble"] },
    { "id": 25, "from": ["призванный","вызванный"], "to": ["summoned"] },
    { "id": 26, "from": ["раскрытый","обнаруженный"], "to": ["revealed"] },
    { "id": 27, "from": ["вовлекать","заниматься","помолвиться"], "to": ["engage"] },
    { "id": 28, "from": ["жалость","сожаление"], "to": ["pity"] },
    { "id": 29, "from": ["редко"], "to": ["seldom"] },
    { "id": 30, "from": ["распутывать","разгадать"], "to": ["unravel"] },
    { "id": 31, "from": ["смотреть пристально","взгляд"], "to": ["gaze"] },
    { "id": 32, "from": ["страсть","увлечение"], "to": ["passion"] },
    { "id": 33, "from": ["эдиль"], "to": ["aedile"] },
    { "id": 34, "from": ["задерживаться","медлить"], "to": ["linger"] },
    { "id": 35, "from": ["качаться","влиять"], "to": ["sway"] },
    { "id": 36, "from": ["грохот","бряцание"], "to": ["clatter"] },
    { "id": 37, "from": ["связь","обязательство","облигация"], "to": ["bond"] }
  ]
}
